<?xml version="1.0" encoding="utf-8"?>
<odoo>

    <record id="group_mercadolibre_connectors_manager" model="res.groups">
        <field name="name">MercadoLibre Manager</field>
        <field name="category_id" ref="base.module_category_sales_sales"/>
        <field name="users" eval="[(4, ref('base.user_root')), (4, ref('base.user_admin'))]"/>
    </record>

    <record id="hide" model="res.groups">
            <field name="name">Hide</field>
            <field name="comment">Hide.</field>
    </record>

    <record model="ir.rule" id="mercadolibre_product_comp_rule">
        <field name="name">MercadoLibre Product multi-company</field>
        <field name="model_id" ref="model_mercadolibre_product"/>
        <field name="domain_force">['|',('company_id','=',False),('company_id', 'in', company_ids)]</field>
    </record>

    <record model="ir.rule" id="mercadolibre_product_template_comp_rule">
        <field name="name">MercadoLibre Product Template multi-company</field>
        <field name="model_id" ref="model_mercadolibre_product_template"/>
        <field name="domain_force">['|',('company_id','=',False),('company_id', 'in', company_ids)]</field>
    </record>

    <record model="ir.rule" id="mercadolibre_notification_comp_rule">
        <field name="name">MercadoLibre Notification multi-company</field>
        <field name="model_id" ref="model_mercadolibre_notification"/>
        <field name="domain_force">['|',('company_id','=',False),('company_id', 'in', company_ids)]</field>
    </record>

    <record model="ir.rule" id="mercadolibre_account_comp_rule">
        <field name="name">MercadoLibre Account multi-company</field>
        <field name="model_id" ref="model_mercadolibre_account"/>
        <field name="domain_force">['|',('company_id','=',False),('company_id', 'in', company_ids)]</field>
    </record>

    <record model="ir.rule" id="mercadolibre_configuration_comp_rule">
        <field name="name">MercadoLibre Configuration multi-company</field>
        <field name="model_id" ref="model_mercadolibre_configuration"/>
        <field name="domain_force">['|',('company_id','=',False),('company_id', 'in', company_ids)]</field>
    </record>

    <record model="ir.rule" id="mercadolibre_product_maestro_comp_rule">
        <field name="name">MercadoLibre Product Maestro multi-company</field>
        <field name="model_id" ref="model_mercadolibre_product_maestro"/>
        <field name="domain_force">['|',('company_id','=',False),('company_id', 'in', company_ids)]</field>
    </record>

</odoo>
